COPYING
COPYING.lesser
MANIFEST.in
NOTICE
README.md
requirements.txt
setup.cfg
setup.py
compiler/__init__.py
compiler/api/__init__.py
compiler/api/compiler.py
compiler/api/source/auth_key.tl
compiler/api/source/main_api.tl
compiler/api/source/sys_msgs.tl
compiler/api/template/combinator.txt
compiler/api/template/type.txt
compiler/docs/__init__.py
compiler/docs/compiler.py
compiler/docs/template/page.txt
compiler/docs/template/toctree.txt
compiler/errors/__init__.py
compiler/errors/compiler.py
compiler/errors/sort.py
compiler/errors/source/303_SEE_OTHER.tsv
compiler/errors/source/400_BAD_REQUEST.tsv
compiler/errors/source/401_UNAUTHORIZED.tsv
compiler/errors/source/403_FORBIDDEN.tsv
compiler/errors/source/406_NOT_ACCEPTABLE.tsv
compiler/errors/source/420_FLOOD.tsv
compiler/errors/source/500_INTERNAL_SERVER_ERROR.tsv
compiler/errors/source/503_SERVICE_UNAVAILABLE.tsv
compiler/errors/template/class.txt
compiler/errors/template/sub_class.txt
pyroru/__init__.py
pyroru/client.py
pyroru/dispatcher.py
pyroru/emoji.py
pyroru/file_id.py
pyroru/filters.py
pyroru/mime_types.py
pyroru/py.typed
pyroru/sync.py
pyroru/utils.py
pyroru.egg-info/PKG-INFO
pyroru.egg-info/SOURCES.txt
pyroru.egg-info/dependency_links.txt
pyroru.egg-info/not-zip-safe
pyroru.egg-info/requires.txt
pyroru.egg-info/top_level.txt
pyroru/connection/__init__.py
pyroru/connection/connection.py
pyroru/connection/transport/__init__.py
pyroru/connection/transport/tcp/__init__.py
pyroru/connection/transport/tcp/tcp.py
pyroru/connection/transport/tcp/tcp_abridged.py
pyroru/connection/transport/tcp/tcp_abridged_o.py
pyroru/connection/transport/tcp/tcp_full.py
pyroru/connection/transport/tcp/tcp_intermediate.py
pyroru/connection/transport/tcp/tcp_intermediate_o.py
pyroru/crypto/__init__.py
pyroru/crypto/aes.py
pyroru/crypto/mtproto.py
pyroru/crypto/prime.py
pyroru/crypto/rsa.py
pyroru/enums/__init__.py
pyroru/enums/auto_name.py
pyroru/enums/chat_action.py
pyroru/enums/chat_event_action.py
pyroru/enums/chat_member_status.py
pyroru/enums/chat_members_filter.py
pyroru/enums/chat_type.py
pyroru/enums/message_entity_type.py
pyroru/enums/message_media_type.py
pyroru/enums/message_service_type.py
